<?xml version="1.0" encoding="UTF-8"?>
<metadata xml:lang="pt"><Esri><CreaDate>20180404</CreaDate><CreaTime>14014800</CreaTime><ArcGISFormat>1.0</ArcGISFormat><SyncOnce>TRUE</SyncOnce><DataProperties><lineage><Process ToolSource="c:\program files (x86)\arcgis\desktop10.4\ArcToolbox\Toolboxes\Data Management Tools.tbx\CalculateField" Date="20180404" Time="140148">CalculateField "Uso do Solo\EEx_Drainage" dissolve_v "dissolve" VB #</Process><Process ToolSource="c:\program files (x86)\arcgis\desktop10.4\ArcToolbox\Toolboxes\Data Management Tools.tbx\CalculateField" Date="20180404" Time="140158">CalculateField "Uso do Solo\EEx_Drainage" dissolve_v "diss" VB #</Process></lineage></DataProperties></Esri></metadata>
